fastdeck/__init__.py
fastdeck/content.py
fastdeck/presentation.py
fastdeck/slide.py
fastdeck-0.1.0.dist-info/LICENSE
fastdeck-0.1.0.dist-info/METADATA
fastdeck-0.1.0.dist-info/WHEEL
fastdeck-0.1.0.dist-info/top_level.txt
fastdeck-0.1.0.dist-info/RECORD
