Metadata-Version: 2.1
Name: fastdeck
Version: 0.1.0
Summary: A library for creating and managing slide decks
Home-page: https://github.com/yourusername/fastdeck
Author: Avratanu Biswas
Author-email: avrab.yt@gmail.com
Classifier: Programming Language :: Python :: 3
Classifier: License :: OSI Approved :: MIT License
Classifier: Operating System :: OS Independent
Requires-Python: >=3.6
License-File: LICENSE
Requires-Dist: beautifulsoup4
Requires-Dist: requests
Requires-Dist: matplotlib
Provides-Extra: full
Requires-Dist: plotly ; extra == 'full'
Requires-Dist: pandas ; extra == 'full'
Requires-Dist: vega ; extra == 'full'
Requires-Dist: vega-datasets ; extra == 'full'
Requires-Dist: altair ; extra == 'full'
